deTEL/__init__.py
deTEL/__main__.py
deTEL/exceptions.py
deTEL/gui.py
deTEL/utils.py
deTEL/eTEL/__init__.py
deTEL/eTEL/workflow/__init__.py
deTEL/eTEL/workflow/danger_mods.csv
deTEL/eTEL/workflow/dataset_report.py
deTEL/eTEL/workflow/eTEL.py
deTEL/eTEL/workflow/extract_peptides.py
deTEL/eTEL/workflow/global_report.py
deTEL/eTEL/workflow/substitution_report.py
deTEL/eTEL/workflow/utils.py
deTEL/eTEL/workflow/templates/substitution_report.html
deTEL/mTEL/__init__.py
deTEL/mTEL/data.py
deTEL/mTEL/mTEL.py
deTEL/mTEL/mcmc.py
deTEL/mTEL/mtem.py
deTEL/rTEL/__init__.py
deTEL/rTEL/open_search.py
deTEL/rTEL/configs/crystal-c.params
deTEL/rTEL/configs/open_search.params
deTEL/rTEL/configs/shepherd.config
deTEL/tRNA_count/ecoli_tRNA_count.csv
deTEL/tRNA_count/yeast_tRNA_count.csv
utility/downloadPRIDE.py
utility/prideCrawler.py
deTELpy-0.1.13.dist-info/LICENSE
deTELpy-0.1.13.dist-info/METADATA
deTELpy-0.1.13.dist-info/WHEEL
deTELpy-0.1.13.dist-info/top_level.txt
deTELpy-0.1.13.dist-info/RECORD
