Metadata-Version: 2.1
Name: deTELpy
Version: 0.1.13
Summary: Python package of the deTEL translation error detection pipeline from mass-spectrometry data
Home-page: https://git.mpi-cbg.de/atplab/detelpy
Author: Cedric Landerer
Author-email: landerer@mpi-cbg.de
License: BSD
Classifier: Development Status :: 1 - Planning
Classifier: Intended Audience :: Science/Research
Classifier: License :: OSI Approved :: BSD License
Classifier: Operating System :: POSIX :: Linux
Classifier: Programming Language :: Python :: 3
Classifier: Programming Language :: Python :: 3.7
License-File: LICENSE
Requires-Dist: pandas ~=1.5.3
Requires-Dist: numpy ~=1.26.3
Requires-Dist: dataclasses ~=0.6
Requires-Dist: pathlib ~=1.0.1
Requires-Dist: biopython ~=1.83
Requires-Dist: numba ~=0.58.1
Requires-Dist: scipy ~=1.11.4
Requires-Dist: tqdm ~=4.66.1
Requires-Dist: seaborn ~=0.13.1
Requires-Dist: matplotlib ~=3.8.2
Requires-Dist: gooey ~=1.0.8
Requires-Dist: python-dateutil ~=2.8.2
Requires-Dist: Jinja2 ~=3.1.3
Requires-Dist: ms-deisotope ~=0.0.53
Requires-Dist: brain-isotopic-distribution ~=1.5.16
Requires-Dist: pebble ~=5.0.6
Requires-Dist: spectrum-utils[iplot] ==0.3.5
Requires-Dist: pythonnet ==3.0.3
